{"decision_calls":5,"execution":"agent_expands_to_visible_actions","expanded_plan_id":"skill-expanded-visible-waypoint-route","expanded_steps":[{"action":{"action":"move_to","arguments":{"navigation":"direct_only","target":{"generation":1,"object_id":"beacon-1"}}},"expected_completion":{"kind":"agent_at_target","parameters":{},"subject":"beacon-1"},"interrupt_on":["waypoint_reached","movement_blocked","target_disappeared"],"preconditions":[{"kind":"target_visible","parameters":{"generation":1},"subject":"beacon-1"}],"step_id":"visit-beacon-1"},{"action":{"action":"move_to","arguments":{"navigation":"direct_only","target":{"generation":1,"object_id":"beacon-2"}}},"expected_completion":{"kind":"agent_at_target","parameters":{},"subject":"beacon-2"},"interrupt_on":["waypoint_reached","movement_blocked","target_disappeared"],"preconditions":[{"kind":"target_visible","parameters":{"generation":1},"subject":"beacon-2"}],"step_id":"visit-beacon-2"},{"action":{"action":"move_to","arguments":{"navigation":"direct_only","target":{"generation":1,"object_id":"beacon-3"}}},"expected_completion":{"kind":"agent_at_target","parameters":{},"subject":"beacon-3"},"interrupt_on":["waypoint_reached","movement_blocked","target_disappeared"],"preconditions":[{"kind":"target_visible","parameters":{"generation":1},"subject":"beacon-3"}],"step_id":"visit-beacon-3"},{"action":{"action":"move_to","arguments":{"navigation":"direct_only","target":{"generation":1,"object_id":"beacon-4"}}},"expected_completion":{"kind":"agent_at_target","parameters":{},"subject":"beacon-4"},"interrupt_on":["waypoint_reached","movement_blocked","target_disappeared"],"preconditions":[{"kind":"target_visible","parameters":{"generation":1},"subject":"beacon-4"}],"step_id":"visit-beacon-4"},{"action":{"action":"move_to","arguments":{"navigation":"direct_only","target":{"generation":1,"object_id":"exit-1"}}},"expected_completion":{"kind":"agent_at_target","parameters":{},"subject":"exit-1"},"interrupt_on":["waypoint_reached","movement_blocked","target_disappeared"],"preconditions":[{"kind":"target_visible","parameters":{"generation":1},"subject":"exit-1"}],"step_id":"visit-exit-1"}],"schema_version":"skill-expansion-evidence.v1","skill_id":"navigation.follow-visible-waypoints-v1","source_observation_seq":0,"source_state_hash":"sha256:8aaef845b7143fb1e69b339080f72bfc20869c173d3597099e2895637b468a2c"}