[{"accepted":true,"applied_ticks":5,"boundary":1,"codes":["decision_accepted","material_interrupt","target_reached"],"end_tick":5,"events":[{"kind":"waypoint_reached","object_id":"beacon-1"}],"response_type":"plan.replace","start_tick":0,"step_id":"visit-beacon-1"},{"accepted":true,"applied_ticks":4,"boundary":2,"codes":["decision_accepted","material_interrupt","target_reached"],"end_tick":9,"events":[{"kind":"waypoint_reached","object_id":"beacon-2"}],"response_type":"plan.continue","start_tick":5,"step_id":"visit-beacon-2"},{"accepted":true,"applied_ticks":4,"boundary":3,"codes":["decision_accepted","material_interrupt","target_reached"],"end_tick":13,"events":[{"kind":"waypoint_reached","object_id":"beacon-3"}],"response_type":"plan.continue","start_tick":9,"step_id":"visit-beacon-3"},{"accepted":true,"applied_ticks":4,"boundary":4,"codes":["decision_accepted","material_interrupt","target_reached"],"end_tick":17,"events":[{"kind":"waypoint_reached","object_id":"beacon-4"}],"response_type":"plan.continue","start_tick":13,"step_id":"visit-beacon-4"},{"accepted":true,"applied_ticks":6,"boundary":5,"codes":["decision_accepted","material_interrupt","target_reached"],"end_tick":23,"events":[{"kind":"waypoint_reached","object_id":"exit-1"}],"response_type":"plan.continue","start_tick":17,"step_id":"visit-exit-1"}]